disparity/__init__.py
disparity/_nbdev.py
disparity/disparity.py
disparity-0.0.5.dist-info/LICENSE
disparity-0.0.5.dist-info/METADATA
disparity-0.0.5.dist-info/WHEEL
disparity-0.0.5.dist-info/entry_points.txt
disparity-0.0.5.dist-info/top_level.txt
disparity-0.0.5.dist-info/RECORD
