Metadata-Version: 2.1
Name: disparity
Version: 0.0.5
Summary: Computing disparity maps
Home-page: https://github.com/justinblaber/disparity/tree/master/
Author: Justin Blaber
Author-email: justin.akira.blaber@gmail.com
License: Apache Software License 2.0
Keywords: disparity
Platform: UNKNOWN
Classifier: Development Status :: 3 - Alpha
Classifier: Intended Audience :: Developers
Classifier: License :: OSI Approved :: Apache Software License
Classifier: Natural Language :: English
Classifier: Programming Language :: Python :: 3.6
Classifier: Programming Language :: Python :: 3.7
Classifier: Programming Language :: Python :: 3.8
Requires-Python: >=3.6
